flake8_super_mario
