Metadata-Version: 2.1
Name: flake8-super-mario
Version: 0.0.2
Summary: A flake8 plugin with super_mario specific validations
Home-page: https://github.com/Melevir/flake8-super-mario
Author: Ilya Lebedev
Author-email: melevir@gmail.com
License: MIT
Keywords: flake8
Platform: UNKNOWN
Classifier: Environment :: Console
Classifier: Framework :: Flake8
Classifier: Operating System :: OS Independent
Classifier: Topic :: Software Development :: Libraries :: Python Modules
Classifier: Topic :: Software Development :: Quality Assurance
Classifier: Programming Language :: Python
Classifier: Programming Language :: Python :: 3.8
